[
  {
    "id": { "$numberLong": "19202103135" },
    "name": "Mohammad Rizwan",
    "account": false
  },
  {
    "id": { "$numberLong": "19202103136" },
    "name": "Babar Azam",
    "account": false
  },
  {
    "id": { "$numberLong": "19202103137" },
    "name": "Nawaz Ahmed",
    "account": false
  },
  {
    "id": { "$numberLong": "19202103138" },
    "name": "Rohit Sharma",
    "account": false
  },
  {
    "id": { "$numberLong": "19202103139" },
    "name": "Virat Kohli",
    "account": false
  }
]
